odoo/addons/sale_restricted_qty/README.rst
odoo/addons/sale_restricted_qty/__init__.py
odoo/addons/sale_restricted_qty/__manifest__.py
odoo/addons/sale_restricted_qty/i18n/fr.po
odoo/addons/sale_restricted_qty/i18n/it.po
odoo/addons/sale_restricted_qty/i18n/sale_order_min_qty.pot
odoo/addons/sale_restricted_qty/i18n/sale_restricted_qty.pot
odoo/addons/sale_restricted_qty/models/__init__.py
odoo/addons/sale_restricted_qty/models/product_category.py
odoo/addons/sale_restricted_qty/models/product_product.py
odoo/addons/sale_restricted_qty/models/product_restricted_qty_mixin.py
odoo/addons/sale_restricted_qty/models/product_template.py
odoo/addons/sale_restricted_qty/models/sale.py
odoo/addons/sale_restricted_qty/readme/CONTRIBUTORS.rst
odoo/addons/sale_restricted_qty/readme/DESCRIPTION.rst
odoo/addons/sale_restricted_qty/readme/USAGE.rst
odoo/addons/sale_restricted_qty/static/description/icon.png
odoo/addons/sale_restricted_qty/static/description/index.html
odoo/addons/sale_restricted_qty/tests/__init__.py
odoo/addons/sale_restricted_qty/tests/test_sale.py
odoo/addons/sale_restricted_qty/views/product_category_views.xml
odoo/addons/sale_restricted_qty/views/product_product_views.xml
odoo/addons/sale_restricted_qty/views/product_template_views.xml
odoo/addons/sale_restricted_qty/views/sale_views.xml
odoo_addon_sale_restricted_qty-16.0.1.0.0.3.dist-info/METADATA
odoo_addon_sale_restricted_qty-16.0.1.0.0.3.dist-info/WHEEL
odoo_addon_sale_restricted_qty-16.0.1.0.0.3.dist-info/top_level.txt
odoo_addon_sale_restricted_qty-16.0.1.0.0.3.dist-info/RECORD
